[
  {
    "ContainingType": "VideosController",
    "Method": "GetVideos",
    "RelativePath": "api/Videos",
    "HttpMethod": "GET",
    "IsController": true,
    "Order": 0,
    "Parameters": [
      {
        "Name": "title",
        "Type": "System.String",
        "IsRequired": false
      },
      {
        "Name": "author",
        "Type": "System.String",
        "IsRequired": false
      },
      {
        "Name": "publishedAfter",
        "Type": "System.Nullable\u00601[[System.DateTime, System.Private.CoreLib, Version=8.0.0.0, Culture=neutral, PublicKeyToken=7cec85d7bea7798e]]",
        "IsRequired": false
      },
      {
        "Name": "q",
        "Type": "System.String",
        "IsRequired": false
      }
    ],
    "ReturnTypes": []
  },
  {
    "ContainingType": "VideosController",
    "Method": "InsertVideo",
    "RelativePath": "api/Videos",
    "HttpMethod": "POST",
    "IsController": true,
    "Order": 0,
    "Parameters": [
      {
        "Name": "video",
        "Type": "YouTubeAPI.Models.Video",
        "IsRequired": true
      }
    ],
    "ReturnTypes": []
  },
  {
    "ContainingType": "VideosController",
    "Method": "UpdateVideo",
    "RelativePath": "api/Videos/{id}",
    "HttpMethod": "PUT",
    "IsController": true,
    "Order": 0,
    "Parameters": [
      {
        "Name": "id",
        "Type": "System.Int32",
        "IsRequired": true
      },
      {
        "Name": "updatedVideo",
        "Type": "YouTubeAPI.Models.Video",
        "IsRequired": true
      }
    ],
    "ReturnTypes": []
  },
  {
    "ContainingType": "VideosController",
    "Method": "DeleteVideo",
    "RelativePath": "api/Videos/{id}",
    "HttpMethod": "DELETE",
    "IsController": true,
    "Order": 0,
    "Parameters": [
      {
        "Name": "id",
        "Type": "System.Int32",
        "IsRequired": true
      }
    ],
    "ReturnTypes": []
  }
]